{"0": {"Block": ["goto", "1"], "{": ["s", "2"], "Program": ["goto", "3"]}, "1": {"#": ["r", 1]}, "2": {"Decls": ["goto", "5"], "{": ["r", 4], "while": ["r", 4], "if2": ["r", 4], "": ["r", 4], "if1": ["r", 4], "}": ["r", 4], "identifier": ["r", 4], "bool": ["r", 4], "float": ["r", 4], "int": ["r", 4]}, "3": {"#": ["acc", -1]}, "4": {"{": ["r", 4], "while": ["r", 4], "if2": ["r", 4], "": ["r", 4], "if1": ["r", 4], "}": ["r", 4], "identifier": ["r", 4], "bool": ["r", 4], "float": ["r", 4], "int": ["r", 4]}, "5": {"Stmts": ["goto", "7"], "bool": ["s", "8"], "Type": ["goto", "9"], "Decl": ["goto", "10"], "int": ["s", "11"], "float": ["s", "12"], "}": ["r", 10], "while": ["r", 10], "if2": ["r", 10], "if1": ["r", 10], "identifier": ["r", 10], "{": ["r", 10]}, "6": {"}": ["r", 10], "while": ["r", 10], "if2": ["r", 10], "if1": ["r", 10], "identifier": ["r", 10], "{": ["r", 10]}, "7": {"Loc": ["goto", "13"], "if1": ["s", "14"], "}": ["s", "15"], "if2": ["s", "16"], "Stmt": ["goto", "17"], "{": ["s", "18"], "identifier": ["s", "19"], "Block": ["goto", "20"], "while": ["s", "21"]}, "8": {"identifier": ["r", 7]}, "9": {"identifier": ["s", "22"]}, "10": {"if2": ["r", 3], "if1": ["r", 3], "": ["r", 3], "}": ["r", 3], "identifier": ["r", 3], "{": ["r", 3], "while": ["r", 3], "float": ["r", 3], "int": ["r", 3], "bool": ["r", 3]}, "11": {"identifier": ["r", 6]}, "12": {"identifier": ["r", 8]}, "13": {"=": ["s", "23"]}, "14": {"(": ["s", "24"]}, "15": {"#": ["r", 2]}, "16": {"(": ["s", "25"]}, "17": {"}": ["r", 9], "if1": ["r", 9], "identifier": ["r", 9], "{": ["r", 9], "while": ["r", 9], "if2": ["r", 9]}, "18": {"Decls": ["goto", "26"], "{": ["r", 4], "while": ["r", 4], "if2": ["r", 4], "": ["r", 4], "if1": ["r", 4], "}": ["r", 4], "identifier": ["r", 4], "bool": ["r", 4], "float": ["r", 4], "int": ["r", 4]}, "19": {"=": ["r", 16]}, "20": {"}": ["r", 15], "if1": ["r", 15], "identifier": ["r", 15], "{": ["r", 15], "while": ["r", 15], "if2": ["r", 15]}, "21": {"(": ["s", "27"]}, "22": {";": ["s", "28"]}, "23": {"Term": ["goto", "29"], "-": ["s", "30"], "true": ["s", "31"], "(": ["s", "32"], "Loc": ["goto", "33"], "Equality": ["goto", "34"], "Expr": ["goto", "35"], "Unary": ["goto", "36"], "constant": ["s", "37"], "identifier": ["s", "38"], "Bool": ["goto", "39"], "Factor": ["goto", "40"], "Join": ["goto", "41"], "false": ["s", "42"], "!": ["s", "43"], "Rel": ["goto", "44"]}, "24": {"Term": ["goto", "45"], "-": ["s", "46"], "true": ["s", "47"], "(": ["s", "48"], "Loc": ["goto", "49"], "Equality": ["goto", "50"], "Expr": ["goto", "51"], "Unary": ["goto", "52"], "constant": ["s", "53"], "identifier": ["s", "54"], "Bool": ["goto", "55"], "Factor": ["goto", "56"], "Join": ["goto", "57"], "false": ["s", "58"], "!": ["s", "59"], "Rel": ["goto", "60"]}, "25": {"Term": ["goto", "45"], "-": ["s", "46"], "true": ["s", "47"], "(": ["s", "48"], "Loc": ["goto", "49"], "Equality": ["goto", "50"], "Expr": ["goto", "51"], "Unary": ["goto", "52"], "constant": ["s", "53"], "identifier": ["s", "54"], "Bool": ["goto", "61"], "Factor": ["goto", "56"], "Join": ["goto", "57"], "false": ["s", "58"], "!": ["s", "59"], "Rel": ["goto", "60"]}, "26": {"Stmts": ["goto", "62"], "bool": ["s", "8"], "Type": ["goto", "9"], "Decl": ["goto", "10"], "int": ["s", "11"], "float": ["s", "12"], "}": ["r", 10], "while": ["r", 10], "if2": ["r", 10], "if1": ["r", 10], "identifier": ["r", 10], "{": ["r", 10]}, "27": {"Term": ["goto", "45"], "-": ["s", "46"], "true": ["s", "47"], "(": ["s", "48"], "Loc": ["goto", "49"], "Equality": ["goto", "50"], "Expr": ["goto", "51"], "Unary": ["goto", "52"], "constant": ["s", "53"], "identifier": ["s", "54"], "Bool": ["goto", "63"], "Factor": ["goto", "56"], "Join": ["goto", "57"], "false": ["s", "58"], "!": ["s", "59"], "Rel": ["goto", "60"]}, "28": {"if2": ["r", 5], "if1": ["r", 5], "}": ["r", 5], "identifier": ["r", 5], "{": ["r", 5], "while": ["r", 5], "float": ["r", 5], "int": ["r", 5], "bool": ["r", 5]}, "29": {"/": ["s", "64"], "*": ["s", "65"], ">=": ["r", 31], "<": ["r", 31], ";": ["r", 31], ">": ["r", 31], "<=": ["r", 31], "||": ["r", 31], "&&": ["r", 31], "!=": ["r", 31], "==": ["r", 31], "-": ["r", 31], "+": ["r", 31]}, "30": {"-": ["s", "30"], "true": ["s", "31"], "(": ["s", "32"], "Loc": ["goto", "33"], "Unary": ["goto", "66"], "constant": ["s", "37"], "identifier": ["s", "38"], "Factor": ["goto", "40"], "false": ["s", "42"], "!": ["s", "43"]}, "31": {">=": ["r", 41], "<": ["r", 41], ";": ["r", 41], ">": ["r", 41], "<=": ["r", 41], "||": ["r", 41], "&&": ["r", 41], "!=": ["r", 41], "==": ["r", 41], "-": ["r", 41], "/": ["r", 41], "*": ["r", 41], "+": ["r", 41]}, "32": {"Term": ["goto", "45"], "-": ["s", "46"], "true": ["s", "47"], "(": ["s", "48"], "Loc": ["goto", "49"], "Equality": ["goto", "50"], "Expr": ["goto", "51"], "Unary": ["goto", "52"], "constant": ["s", "53"], "identifier": ["s", "54"], "Bool": ["goto", "67"], "Factor": ["goto", "56"], "Join": ["goto", "57"], "false": ["s", "58"], "!": ["s", "59"], "Rel": ["goto", "60"]}, "33": {">=": ["r", 39], "<": ["r", 39], ";": ["r", 39], ">": ["r", 39], "<=": ["r", 39], "||": ["r", 39], "&&": ["r", 39], "!=": ["r", 39], "==": ["r", 39], "-": ["r", 39], "/": ["r", 39], "*": ["r", 39], "+": ["r", 39]}, "34": {"!=": ["s", "68"], "==": ["s", "69"], ";": ["r", 20], "||": ["r", 20], "&&": ["r", 20]}, "35": {"-": ["s", "70"], "<=": ["s", "71"], "<": ["s", "72"], ">=": ["s", "73"], "+": ["s", "74"], ">": ["s", "75"], ";": ["r", 28], "||": ["r", 28], "&&": ["r", 28], "!=": ["r", 28], "==": ["r", 28]}, "36": {">=": ["r", 34], "<": ["r", 34], ";": ["r", 34], ">": ["r", 34], "<=": ["r", 34], "||": ["r", 34], "&&": ["r", 34], "!=": ["r", 34], "==": ["r", 34], "-": ["r", 34], "/": ["r", 34], "*": ["r", 34], "+": ["r", 34]}, "37": {">=": ["r", 40], "<": ["r", 40], ";": ["r", 40], ">": ["r", 40], "<=": ["r", 40], "||": ["r", 40], "&&": ["r", 40], "!=": ["r", 40], "==": ["r", 40], "-": ["r", 40], "/": ["r", 40], "*": ["r", 40], "+": ["r", 40]}, "38": {">=": ["r", 16], "<": ["r", 16], ";": ["r", 16], ">": ["r", 16], "<=": ["r", 16], "||": ["r", 16], "&&": ["r", 16], "!=": ["r", 16], "==": ["r", 16], "-": ["r", 16], "/": ["r", 16], "*": ["r", 16], "+": ["r", 16]}, "39": {";": ["s", "76"], "||": ["s", "77"]}, "40": {">=": ["r", 37], "<": ["r", 37], ";": ["r", 37], ">": ["r", 37], "<=": ["r", 37], "||": ["r", 37], "&&": ["r", 37], "!=": ["r", 37], "==": ["r", 37], "-": ["r", 37], "/": ["r", 37], "*": ["r", 37], "+": ["r", 37]}, "41": {"&&": ["s", "78"], ";": ["r", 18], "||": ["r", 18]}, "42": {">=": ["r", 42], "<": ["r", 42], ";": ["r", 42], ">": ["r", 42], "<=": ["r", 42], "||": ["r", 42], "&&": ["r", 42], "!=": ["r", 42], "==": ["r", 42], "-": ["r", 42], "/": ["r", 42], "*": ["r", 42], "+": ["r", 42]}, "43": {"-": ["s", "30"], "true": ["s", "31"], "(": ["s", "32"], "Loc": ["goto", "33"], "Unary": ["goto", "79"], "constant": ["s", "37"], "identifier": ["s", "38"], "Factor": ["goto", "40"], "false": ["s", "42"], "!": ["s", "43"]}, "44": {";": ["r", 23], "||": ["r", 23], "&&": ["r", 23], "!=": ["r", 23], "==": ["r", 23]}, "45": {"/": ["s", "80"], "*": ["s", "81"], "<": ["r", 31], ")": ["r", 31], ">": ["r", 31], "<=": ["r", 31], ">=": ["r", 31], "&&": ["r", 31], "!=": ["r", 31], "==": ["r", 31], "+": ["r", 31], "-": ["r", 31], "||": ["r", 31]}, "46": {"-": ["s", "46"], "true": ["s", "47"], "(": ["s", "48"], "Loc": ["goto", "49"], "Unary": ["goto", "82"], "constant": ["s", "53"], "identifier": ["s", "54"], "Factor": ["goto", "56"], "false": ["s", "58"], "!": ["s", "59"]}, "47": {"<": ["r", 41], ")": ["r", 41], ">": ["r", 41], "<=": ["r", 41], ">=": ["r", 41], "&&": ["r", 41], "!=": ["r", 41], "==": ["r", 41], "+": ["r", 41], "-": ["r", 41], "*": ["r", 41], "/": ["r", 41], "||": ["r", 41]}, "48": {"Term": ["goto", "45"], "-": ["s", "46"], "true": ["s", "47"], "(": ["s", "48"], "Loc": ["goto", "49"], "Equality": ["goto", "50"], "Expr": ["goto", "51"], "Unary": ["goto", "52"], "constant": ["s", "53"], "identifier": ["s", "54"], "Bool": ["goto", "83"], "Factor": ["goto", "56"], "Join": ["goto", "57"], "false": ["s", "58"], "!": ["s", "59"], "Rel": ["goto", "60"]}, "49": {"<": ["r", 39], ")": ["r", 39], ">": ["r", 39], "<=": ["r", 39], ">=": ["r", 39], "&&": ["r", 39], "!=": ["r", 39], "==": ["r", 39], "+": ["r", 39], "-": ["r", 39], "*": ["r", 39], "/": ["r", 39], "||": ["r", 39]}, "50": {"!=": ["s", "84"], "==": ["s", "85"], ")": ["r", 20], "&&": ["r", 20], "||": ["r", 20]}, "51": {"-": ["s", "86"], "<=": ["s", "87"], "<": ["s", "88"], ">=": ["s", "89"], "+": ["s", "90"], ">": ["s", "91"], ")": ["r", 28], "&&": ["r", 28], "!=": ["r", 28], "==": ["r", 28], "||": ["r", 28]}, "52": {"<": ["r", 34], ")": ["r", 34], ">": ["r", 34], "<=": ["r", 34], ">=": ["r", 34], "&&": ["r", 34], "!=": ["r", 34], "==": ["r", 34], "+": ["r", 34], "-": ["r", 34], "*": ["r", 34], "/": ["r", 34], "||": ["r", 34]}, "53": {"<": ["r", 40], ")": ["r", 40], ">": ["r", 40], "<=": ["r", 40], ">=": ["r", 40], "&&": ["r", 40], "!=": ["r", 40], "==": ["r", 40], "+": ["r", 40], "-": ["r", 40], "*": ["r", 40], "/": ["r", 40], "||": ["r", 40]}, "54": {"<": ["r", 16], ")": ["r", 16], ">": ["r", 16], "<=": ["r", 16], ">=": ["r", 16], "&&": ["r", 16], "!=": ["r", 16], "==": ["r", 16], "+": ["r", 16], "-": ["r", 16], "*": ["r", 16], "/": ["r", 16], "||": ["r", 16]}, "55": {"||": ["s", "92"], ")": ["s", "93"]}, "56": {"<": ["r", 37], ")": ["r", 37], ">": ["r", 37], "<=": ["r", 37], ">=": ["r", 37], "&&": ["r", 37], "!=": ["r", 37], "==": ["r", 37], "+": ["r", 37], "-": ["r", 37], "*": ["r", 37], "/": ["r", 37], "||": ["r", 37]}, "57": {"&&": ["s", "94"], ")": ["r", 18], "||": ["r", 18]}, "58": {"<": ["r", 42], ")": ["r", 42], ">": ["r", 42], "<=": ["r", 42], ">=": ["r", 42], "&&": ["r", 42], "!=": ["r", 42], "==": ["r", 42], "+": ["r", 42], "-": ["r", 42], "*": ["r", 42], "/": ["r", 42], "||": ["r", 42]}, "59": {"-": ["s", "46"], "true": ["s", "47"], "(": ["s", "48"], "Loc": ["goto", "49"], "Unary": ["goto", "95"], "constant": ["s", "53"], "identifier": ["s", "54"], "Factor": ["goto", "56"], "false": ["s", "58"], "!": ["s", "59"]}, "60": {")": ["r", 23], "&&": ["r", 23], "!=": ["r", 23], "==": ["r", 23], "||": ["r", 23]}, "61": {"||": ["s", "92"], ")": ["s", "96"]}, "62": {"Loc": ["goto", "13"], "if1": ["s", "14"], "}": ["s", "97"], "if2": ["s", "16"], "Stmt": ["goto", "17"], "{": ["s", "18"], "identifier": ["s", "19"], "Block": ["goto", "20"], "while": ["s", "21"]}, "63": {"||": ["s", "92"], ")": ["s", "98"]}, "64": {"-": ["s", "30"], "true": ["s", "31"], "(": ["s", "32"], "Loc": ["goto", "33"], "Unary": ["goto", "99"], "constant": ["s", "37"], "identifier": ["s", "38"], "Factor": ["goto", "40"], "false": ["s", "42"], "!": ["s", "43"]}, "65": {"-": ["s", "30"], "true": ["s", "31"], "(": ["s", "32"], "Loc": ["goto", "33"], "Unary": ["goto", "100"], "constant": ["s", "37"], "identifier": ["s", "38"], "Factor": ["goto", "40"], "false": ["s", "42"], "!": ["s", "43"]}, "66": {">=": ["r", 36], "<": ["r", 36], ";": ["r", 36], ">": ["r", 36], "<=": ["r", 36], "||": ["r", 36], "&&": ["r", 36], "!=": ["r", 36], "==": ["r", 36], "-": ["r", 36], "/": ["r", 36], "*": ["r", 36], "+": ["r", 36]}, "67": {"||": ["s", "92"], ")": ["s", "101"]}, "68": {"Term": ["goto", "29"], "-": ["s", "30"], "true": ["s", "31"], "(": ["s", "32"], "Loc": ["goto", "33"], "Expr": ["goto", "35"], "Unary": ["goto", "36"], "constant": ["s", "37"], "identifier": ["s", "38"], "Factor": ["goto", "40"], "false": ["s", "42"], "!": ["s", "43"], "Rel": ["goto", "102"]}, "69": {"Term": ["goto", "29"], "-": ["s", "30"], "true": ["s", "31"], "(": ["s", "32"], "Loc": ["goto", "33"], "Expr": ["goto", "35"], "Unary": ["goto", "36"], "constant": ["s", "37"], "identifier": ["s", "38"], "Factor": ["goto", "40"], "false": ["s", "42"], "!": ["s", "43"], "Rel": ["goto", "103"]}, "70": {"Term": ["goto", "104"], "-": ["s", "30"], "true": ["s", "31"], "(": ["s", "32"], "Loc": ["goto", "33"], "Unary": ["goto", "36"], "constant": ["s", "37"], "identifier": ["s", "38"], "Factor": ["goto", "40"], "false": ["s", "42"], "!": ["s", "43"]}, "71": {"Term": ["goto", "105"], "-": ["s", "106"], "(": ["s", "107"], "true": ["s", "108"], "Loc": ["goto", "109"], "Expr": ["goto", "110"], "Unary": ["goto", "111"], "constant": ["s", "112"], "identifier": ["s", "113"], "Factor": ["goto", "114"], "false": ["s", "115"], "!": ["s", "116"]}, "72": {"Term": ["goto", "105"], "-": ["s", "106"], "(": ["s", "107"], "true": ["s", "108"], "Loc": ["goto", "109"], "Expr": ["goto", "117"], "Unary": ["goto", "111"], "constant": ["s", "112"], "identifier": ["s", "113"], "Factor": ["goto", "114"], "false": ["s", "115"], "!": ["s", "116"]}, "73": {"Term": ["goto", "105"], "-": ["s", "106"], "(": ["s", "107"], "true": ["s", "108"], "Loc": ["goto", "109"], "Expr": ["goto", "118"], "Unary": ["goto", "111"], "constant": ["s", "112"], "identifier": ["s", "113"], "Factor": ["goto", "114"], "false": ["s", "115"], "!": ["s", "116"]}, "74": {"Term": ["goto", "119"], "-": ["s", "30"], "true": ["s", "31"], "(": ["s", "32"], "Loc": ["goto", "33"], "Unary": ["goto", "36"], "constant": ["s", "37"], "identifier": ["s", "38"], "Factor": ["goto", "40"], "false": ["s", "42"], "!": ["s", "43"]}, "75": {"Term": ["goto", "105"], "-": ["s", "106"], "(": ["s", "107"], "true": ["s", "108"], "Loc": ["goto", "109"], "Expr": ["goto", "120"], "Unary": ["goto", "111"], "constant": ["s", "112"], "identifier": ["s", "113"], "Factor": ["goto", "114"], "false": ["s", "115"], "!": ["s", "116"]}, "76": {"}": ["r", 11], "if1": ["r", 11], "identifier": ["r", 11], "{": ["r", 11], "while": ["r", 11], "if2": ["r", 11]}, "77": {"Term": ["goto", "29"], "-": ["s", "30"], "true": ["s", "31"], "(": ["s", "32"], "Loc": ["goto", "33"], "Equality": ["goto", "34"], "Expr": ["goto", "35"], "Unary": ["goto", "36"], "constant": ["s", "37"], "identifier": ["s", "38"], "Factor": ["goto", "40"], "Join": ["goto", "121"], "false": ["s", "42"], "!": ["s", "43"], "Rel": ["goto", "44"]}, "78": {"Term": ["goto", "29"], "-": ["s", "30"], "true": ["s", "31"], "(": ["s", "32"], "Loc": ["goto", "33"], "Equality": ["goto", "122"], "Expr": ["goto", "35"], "Unary": ["goto", "36"], "constant": ["s", "37"], "identifier": ["s", "38"], "Factor": ["goto", "40"], "false": ["s", "42"], "!": ["s", "43"], "Rel": ["goto", "44"]}, "79": {">=": ["r", 35], "<": ["r", 35], ";": ["r", 35], ">": ["r", 35], "<=": ["r", 35], "||": ["r", 35], "&&": ["r", 35], "!=": ["r", 35], "==": ["r", 35], "-": ["r", 35], "/": ["r", 35], "*": ["r", 35], "+": ["r", 35]}, "80": {"-": ["s", "46"], "true": ["s", "47"], "(": ["s", "48"], "Loc": ["goto", "49"], "Unary": ["goto", "123"], "constant": ["s", "53"], "identifier": ["s", "54"], "Factor": ["goto", "56"], "false": ["s", "58"], "!": ["s", "59"]}, "81": {"-": ["s", "46"], "true": ["s", "47"], "(": ["s", "48"], "Loc": ["goto", "49"], "Unary": ["goto", "124"], "constant": ["s", "53"], "identifier": ["s", "54"], "Factor": ["goto", "56"], "false": ["s", "58"], "!": ["s", "59"]}, "82": {"<": ["r", 36], ")": ["r", 36], ">": ["r", 36], "<=": ["r", 36], ">=": ["r", 36], "&&": ["r", 36], "!=": ["r", 36], "==": ["r", 36], "+": ["r", 36], "-": ["r", 36], "*": ["r", 36], "/": ["r", 36], "||": ["r", 36]}, "83": {"||": ["s", "92"], ")": ["s", "125"]}, "84": {"Term": ["goto", "45"], "-": ["s", "46"], "true": ["s", "47"], "(": ["s", "48"], "Loc": ["goto", "49"], "Expr": ["goto", "51"], "Unary": ["goto", "52"], "constant": ["s", "53"], "identifier": ["s", "54"], "Factor": ["goto", "56"], "false": ["s", "58"], "!": ["s", "59"], "Rel": ["goto", "126"]}, "85": {"Term": ["goto", "45"], "-": ["s", "46"], "true": ["s", "47"], "(": ["s", "48"], "Loc": ["goto", "49"], "Expr": ["goto", "51"], "Unary": ["goto", "52"], "constant": ["s", "53"], "identifier": ["s", "54"], "Factor": ["goto", "56"], "false": ["s", "58"], "!": ["s", "59"], "Rel": ["goto", "127"]}, "86": {"Term": ["goto", "128"], "-": ["s", "46"], "true": ["s", "47"], "(": ["s", "48"], "Loc": ["goto", "49"], "Unary": ["goto", "52"], "constant": ["s", "53"], "identifier": ["s", "54"], "Factor": ["goto", "56"], "false": ["s", "58"], "!": ["s", "59"]}, "87": {"Term": ["goto", "129"], "-": ["s", "130"], "true": ["s", "131"], "(": ["s", "132"], "Loc": ["goto", "133"], "Expr": ["goto", "134"], "Unary": ["goto", "135"], "constant": ["s", "136"], "identifier": ["s", "137"], "Factor": ["goto", "138"], "false": ["s", "139"], "!": ["s", "140"]}, "88": {"Term": ["goto", "129"], "-": ["s", "130"], "true": ["s", "131"], "(": ["s", "132"], "Loc": ["goto", "133"], "Expr": ["goto", "141"], "Unary": ["goto", "135"], "constant": ["s", "136"], "identifier": ["s", "137"], "Factor": ["goto", "138"], "false": ["s", "139"], "!": ["s", "140"]}, "89": {"Term": ["goto", "129"], "-": ["s", "130"], "true": ["s", "131"], "(": ["s", "132"], "Loc": ["goto", "133"], "Expr": ["goto", "142"], "Unary": ["goto", "135"], "constant": ["s", "136"], "identifier": ["s", "137"], "Factor": ["goto", "138"], "false": ["s", "139"], "!": ["s", "140"]}, "90": {"Term": ["goto", "143"], "-": ["s", "46"], "true": ["s", "47"], "(": ["s", "48"], "Loc": ["goto", "49"], "Unary": ["goto", "52"], "constant": ["s", "53"], "identifier": ["s", "54"], "Factor": ["goto", "56"], "false": ["s", "58"], "!": ["s", "59"]}, "91": {"Term": ["goto", "129"], "-": ["s", "130"], "true": ["s", "131"], "(": ["s", "132"], "Loc": ["goto", "133"], "Expr": ["goto", "144"], "Unary": ["goto", "135"], "constant": ["s", "136"], "identifier": ["s", "137"], "Factor": ["goto", "138"], "false": ["s", "139"], "!": ["s", "140"]}, "92": {"Term": ["goto", "45"], "-": ["s", "46"], "true": ["s", "47"], "(": ["s", "48"], "Loc": ["goto", "49"], "Equality": ["goto", "50"], "Expr": ["goto", "51"], "Unary": ["goto", "52"], "constant": ["s", "53"], "identifier": ["s", "54"], "Factor": ["goto", "56"], "Join": ["goto", "145"], "false": ["s", "58"], "!": ["s", "59"], "Rel": ["goto", "60"]}, "93": {"Loc": ["goto", "13"], "if1": ["s", "14"], "if2": ["s", "16"], "Stmt": ["goto", "146"], "{": ["s", "18"], "identifier": ["s", "19"], "while": ["s", "21"], "Block": ["goto", "20"]}, "94": {"Term": ["goto", "45"], "-": ["s", "46"], "true": ["s", "47"], "(": ["s", "48"], "Loc": ["goto", "49"], "Equality": ["goto", "147"], "Expr": ["goto", "51"], "Unary": ["goto", "52"], "constant": ["s", "53"], "identifier": ["s", "54"], "Factor": ["goto", "56"], "false": ["s", "58"], "!": ["s", "59"], "Rel": ["goto", "60"]}, "95": {"<": ["r", 35], ")": ["r", 35], ">": ["r", 35], "<=": ["r", 35], ">=": ["r", 35], "&&": ["r", 35], "!=": ["r", 35], "==": ["r", 35], "+": ["r", 35], "-": ["r", 35], "*": ["r", 35], "/": ["r", 35], "||": ["r", 35]}, "96": {"Loc": ["goto", "148"], "if1": ["s", "149"], "if2": ["s", "150"], "Stmt": ["goto", "151"], "{": ["s", "152"], "identifier": ["s", "19"], "while": ["s", "153"], "Block": ["goto", "154"]}, "97": {"}": ["r", 2], "if1": ["r", 2], "identifier": ["r", 2], "{": ["r", 2], "while": ["r", 2], "if2": ["r", 2]}, "98": {"Loc": ["goto", "13"], "if1": ["s", "14"], "if2": ["s", "16"], "Stmt": ["goto", "155"], "{": ["s", "18"], "identifier": ["s", "19"], "while": ["s", "21"], "Block": ["goto", "20"]}, "99": {">=": ["r", 33], "<": ["r", 33], ";": ["r", 33], ">": ["r", 33], "<=": ["r", 33], "||": ["r", 33], "&&": ["r", 33], "!=": ["r", 33], "==": ["r", 33], "-": ["r", 33], "/": ["r", 33], "*": ["r", 33], "+": ["r", 33]}, "100": {">=": ["r", 32], "<": ["r", 32], ";": ["r", 32], ">": ["r", 32], "<=": ["r", 32], "||": ["r", 32], "&&": ["r", 32], "!=": ["r", 32], "==": ["r", 32], "-": ["r", 32], "/": ["r", 32], "*": ["r", 32], "+": ["r", 32]}, "101": {">=": ["r", 38], "<": ["r", 38], ";": ["r", 38], ">": ["r", 38], "<=": ["r", 38], "||": ["r", 38], "&&": ["r", 38], "!=": ["r", 38], "==": ["r", 38], "-": ["r", 38], "/": ["r", 38], "*": ["r", 38], "+": ["r", 38]}, "102": {";": ["r", 22], "||": ["r", 22], "&&": ["r", 22], "!=": ["r", 22], "==": ["r", 22]}, "103": {";": ["r", 21], "||": ["r", 21], "&&": ["r", 21], "!=": ["r", 21], "==": ["r", 21]}, "104": {"/": ["s", "64"], "*": ["s", "65"], ">=": ["r", 30], "<": ["r", 30], ";": ["r", 30], ">": ["r", 30], "<=": ["r", 30], "||": ["r", 30], "&&": ["r", 30], "!=": ["r", 30], "==": ["r", 30], "-": ["r", 30], "+": ["r", 30]}, "105": {"/": ["s", "156"], "*": ["s", "157"], ";": ["r", 31], "||": ["r", 31], "&&": ["r", 31], "!=": ["r", 31], "==": ["r", 31], "-": ["r", 31], "+": ["r", 31]}, "106": {"(": ["s", "107"], "-": ["s", "106"], "true": ["s", "108"], "Loc": ["goto", "109"], "Unary": ["goto", "158"], "constant": ["s", "112"], "identifier": ["s", "113"], "Factor": ["goto", "114"], "false": ["s", "115"], "!": ["s", "116"]}, "107": {"Term": ["goto", "45"], "-": ["s", "46"], "true": ["s", "47"], "(": ["s", "48"], "Loc": ["goto", "49"], "Equality": ["goto", "50"], "Expr": ["goto", "51"], "Unary": ["goto", "52"], "constant": ["s", "53"], "identifier": ["s", "54"], "Bool": ["goto", "159"], "Factor": ["goto", "56"], "Join": ["goto", "57"], "false": ["s", "58"], "!": ["s", "59"], "Rel": ["goto", "60"]}, "108": {";": ["r", 41], "||": ["r", 41], "&&": ["r", 41], "!=": ["r", 41], "==": ["r", 41], "-": ["r", 41], "/": ["r", 41], "*": ["r", 41], "+": ["r", 41]}, "109": {";": ["r", 39], "||": ["r", 39], "&&": ["r", 39], "!=": ["r", 39], "==": ["r", 39], "-": ["r", 39], "/": ["r", 39], "*": ["r", 39], "+": ["r", 39]}, "110": {"-": ["s", "160"], "+": ["s", "161"], ";": ["r", 25], "||": ["r", 25], "&&": ["r", 25], "!=": ["r", 25], "==": ["r", 25]}, "111": {";": ["r", 34], "||": ["r", 34], "&&": ["r", 34], "!=": ["r", 34], "==": ["r", 34], "-": ["r", 34], "/": ["r", 34], "*": ["r", 34], "+": ["r", 34]}, "112": {";": ["r", 40], "||": ["r", 40], "&&": ["r", 40], "!=": ["r", 40], "==": ["r", 40], "-": ["r", 40], "/": ["r", 40], "*": ["r", 40], "+": ["r", 40]}, "113": {";": ["r", 16], "||": ["r", 16], "&&": ["r", 16], "!=": ["r", 16], "==": ["r", 16], "-": ["r", 16], "/": ["r", 16], "*": ["r", 16], "+": ["r", 16]}, "114": {";": ["r", 37], "||": ["r", 37], "&&": ["r", 37], "!=": ["r", 37], "==": ["r", 37], "-": ["r", 37], "/": ["r", 37], "*": ["r", 37], "+": ["r", 37]}, "115": {";": ["r", 42], "||": ["r", 42], "&&": ["r", 42], "!=": ["r", 42], "==": ["r", 42], "-": ["r", 42], "/": ["r", 42], "*": ["r", 42], "+": ["r", 42]}, "116": {"(": ["s", "107"], "-": ["s", "106"], "true": ["s", "108"], "Loc": ["goto", "109"], "Unary": ["goto", "162"], "constant": ["s", "112"], "identifier": ["s", "113"], "Factor": ["goto", "114"], "false": ["s", "115"], "!": ["s", "116"]}, "117": {"-": ["s", "160"], "+": ["s", "161"], ";": ["r", 24], "||": ["r", 24], "&&": ["r", 24], "!=": ["r", 24], "==": ["r", 24]}, "118": {"-": ["s", "160"], "+": ["s", "161"], ";": ["r", 27], "||": ["r", 27], "&&": ["r", 27], "!=": ["r", 27], "==": ["r", 27]}, "119": {"/": ["s", "64"], "*": ["s", "65"], ">=": ["r", 29], "<": ["r", 29], ";": ["r", 29], ">": ["r", 29], "<=": ["r", 29], "||": ["r", 29], "&&": ["r", 29], "!=": ["r", 29], "==": ["r", 29], "-": ["r", 29], "+": ["r", 29]}, "120": {"-": ["s", "160"], "+": ["s", "161"], ";": ["r", 26], "||": ["r", 26], "&&": ["r", 26], "!=": ["r", 26], "==": ["r", 26]}, "121": {"&&": ["s", "78"], ";": ["r", 17], "||": ["r", 17]}, "122": {"!=": ["s", "68"], "==": ["s", "69"], ";": ["r", 19], "||": ["r", 19], "&&": ["r", 19]}, "123": {"<": ["r", 33], ")": ["r", 33], ">": ["r", 33], "<=": ["r", 33], ">=": ["r", 33], "&&": ["r", 33], "!=": ["r", 33], "==": ["r", 33], "+": ["r", 33], "-": ["r", 33], "*": ["r", 33], "/": ["r", 33], "||": ["r", 33]}, "124": {"<": ["r", 32], ")": ["r", 32], ">": ["r", 32], "<=": ["r", 32], ">=": ["r", 32], "&&": ["r", 32], "!=": ["r", 32], "==": ["r", 32], "+": ["r", 32], "-": ["r", 32], "*": ["r", 32], "/": ["r", 32], "||": ["r", 32]}, "125": {"<": ["r", 38], ")": ["r", 38], ">": ["r", 38], "<=": ["r", 38], ">=": ["r", 38], "&&": ["r", 38], "!=": ["r", 38], "==": ["r", 38], "+": ["r", 38], "-": ["r", 38], "*": ["r", 38], "/": ["r", 38], "||": ["r", 38]}, "126": {")": ["r", 22], "&&": ["r", 22], "!=": ["r", 22], "==": ["r", 22], "||": ["r", 22]}, "127": {")": ["r", 21], "&&": ["r", 21], "!=": ["r", 21], "==": ["r", 21], "||": ["r", 21]}, "128": {"/": ["s", "80"], "*": ["s", "81"], "<": ["r", 30], ")": ["r", 30], ">": ["r", 30], "<=": ["r", 30], ">=": ["r", 30], "&&": ["r", 30], "!=": ["r", 30], "==": ["r", 30], "+": ["r", 30], "-": ["r", 30], "||": ["r", 30]}, "129": {"/": ["s", "163"], "*": ["s", "164"], ")": ["r", 31], "&&": ["r", 31], "!=": ["r", 31], "==": ["r", 31], "||": ["r", 31], "-": ["r", 31], "+": ["r", 31]}, "130": {"-": ["s", "130"], "true": ["s", "131"], "(": ["s", "132"], "Loc": ["goto", "133"], "Unary": ["goto", "165"], "constant": ["s", "136"], "identifier": ["s", "137"], "Factor": ["goto", "138"], "false": ["s", "139"], "!": ["s", "140"]}, "131": {")": ["r", 41], "&&": ["r", 41], "!=": ["r", 41], "==": ["r", 41], "||": ["r", 41], "-": ["r", 41], "/": ["r", 41], "*": ["r", 41], "+": ["r", 41]}, "132": {"Term": ["goto", "45"], "-": ["s", "46"], "true": ["s", "47"], "(": ["s", "48"], "Loc": ["goto", "49"], "Equality": ["goto", "50"], "Expr": ["goto", "51"], "Unary": ["goto", "52"], "constant": ["s", "53"], "identifier": ["s", "54"], "Bool": ["goto", "166"], "Factor": ["goto", "56"], "Join": ["goto", "57"], "false": ["s", "58"], "!": ["s", "59"], "Rel": ["goto", "60"]}, "133": {")": ["r", 39], "&&": ["r", 39], "!=": ["r", 39], "==": ["r", 39], "||": ["r", 39], "-": ["r", 39], "/": ["r", 39], "*": ["r", 39], "+": ["r", 39]}, "134": {"-": ["s", "167"], "+": ["s", "168"], ")": ["r", 25], "&&": ["r", 25], "!=": ["r", 25], "==": ["r", 25], "||": ["r", 25]}, "135": {")": ["r", 34], "&&": ["r", 34], "!=": ["r", 34], "==": ["r", 34], "||": ["r", 34], "-": ["r", 34], "/": ["r", 34], "*": ["r", 34], "+": ["r", 34]}, "136": {")": ["r", 40], "&&": ["r", 40], "!=": ["r", 40], "==": ["r", 40], "||": ["r", 40], "-": ["r", 40], "/": ["r", 40], "*": ["r", 40], "+": ["r", 40]}, "137": {")": ["r", 16], "&&": ["r", 16], "!=": ["r", 16], "==": ["r", 16], "||": ["r", 16], "-": ["r", 16], "/": ["r", 16], "*": ["r", 16], "+": ["r", 16]}, "138": {")": ["r", 37], "&&": ["r", 37], "!=": ["r", 37], "==": ["r", 37], "||": ["r", 37], "-": ["r", 37], "/": ["r", 37], "*": ["r", 37], "+": ["r", 37]}, "139": {")": ["r", 42], "&&": ["r", 42], "!=": ["r", 42], "==": ["r", 42], "||": ["r", 42], "-": ["r", 42], "/": ["r", 42], "*": ["r", 42], "+": ["r", 42]}, "140": {"-": ["s", "130"], "true": ["s", "131"], "(": ["s", "132"], "Loc": ["goto", "133"], "Unary": ["goto", "169"], "constant": ["s", "136"], "identifier": ["s", "137"], "Factor": ["goto", "138"], "false": ["s", "139"], "!": ["s", "140"]}, "141": {"-": ["s", "167"], "+": ["s", "168"], ")": ["r", 24], "&&": ["r", 24], "!=": ["r", 24], "==": ["r", 24], "||": ["r", 24]}, "142": {"-": ["s", "167"], "+": ["s", "168"], ")": ["r", 27], "&&": ["r", 27], "!=": ["r", 27], "==": ["r", 27], "||": ["r", 27]}, "143": {"/": ["s", "80"], "*": ["s", "81"], "<": ["r", 29], ")": ["r", 29], ">": ["r", 29], "<=": ["r", 29], ">=": ["r", 29], "&&": ["r", 29], "!=": ["r", 29], "==": ["r", 29], "+": ["r", 29], "-": ["r", 29], "||": ["r", 29]}, "144": {"-": ["s", "167"], "+": ["s", "168"], ")": ["r", 26], "&&": ["r", 26], "!=": ["r", 26], "==": ["r", 26], "||": ["r", 26]}, "145": {"&&": ["s", "94"], ")": ["r", 17], "||": ["r", 17]}, "146": {"}": ["r", 12], "if1": ["r", 12], "identifier": ["r", 12], "{": ["r", 12], "while": ["r", 12], "if2": ["r", 12]}, "147": {"!=": ["s", "84"], "==": ["s", "85"], ")": ["r", 19], "&&": ["r", 19], "||": ["r", 19]}, "148": {"=": ["s", "170"]}, "149": {"(": ["s", "171"]}, "150": {"(": ["s", "172"]}, "151": {"else": ["s", "173"]}, "152": {"Decls": ["goto", "174"], "{": ["r", 4], "while": ["r", 4], "if2": ["r", 4], "": ["r", 4], "if1": ["r", 4], "}": ["r", 4], "identifier": ["r", 4], "bool": ["r", 4], "float": ["r", 4], "int": ["r", 4]}, "153": {"(": ["s", "175"]}, "154": {"else": ["r", 15]}, "155": {"}": ["r", 14], "if1": ["r", 14], "identifier": ["r", 14], "{": ["r", 14], "while": ["r", 14], "if2": ["r", 14]}, "156": {"(": ["s", "107"], "-": ["s", "106"], "true": ["s", "108"], "Loc": ["goto", "109"], "Unary": ["goto", "176"], "constant": ["s", "112"], "identifier": ["s", "113"], "Factor": ["goto", "114"], "false": ["s", "115"], "!": ["s", "116"]}, "157": {"(": ["s", "107"], "-": ["s", "106"], "true": ["s", "108"], "Loc": ["goto", "109"], "Unary": ["goto", "177"], "constant": ["s", "112"], "identifier": ["s", "113"], "Factor": ["goto", "114"], "false": ["s", "115"], "!": ["s", "116"]}, "158": {";": ["r", 36], "||": ["r", 36], "&&": ["r", 36], "!=": ["r", 36], "==": ["r", 36], "-": ["r", 36], "/": ["r", 36], "*": ["r", 36], "+": ["r", 36]}, "159": {"||": ["s", "92"], ")": ["s", "178"]}, "160": {"Term": ["goto", "179"], "-": ["s", "106"], "(": ["s", "107"], "true": ["s", "108"], "Loc": ["goto", "109"], "Unary": ["goto", "111"], "constant": ["s", "112"], "identifier": ["s", "113"], "Factor": ["goto", "114"], "false": ["s", "115"], "!": ["s", "116"]}, "161": {"Term": ["goto", "180"], "-": ["s", "106"], "(": ["s", "107"], "true": ["s", "108"], "Loc": ["goto", "109"], "Unary": ["goto", "111"], "constant": ["s", "112"], "identifier": ["s", "113"], "Factor": ["goto", "114"], "false": ["s", "115"], "!": ["s", "116"]}, "162": {";": ["r", 35], "||": ["r", 35], "&&": ["r", 35], "!=": ["r", 35], "==": ["r", 35], "-": ["r", 35], "/": ["r", 35], "*": ["r", 35], "+": ["r", 35]}, "163": {"-": ["s", "130"], "true": ["s", "131"], "(": ["s", "132"], "Loc": ["goto", "133"], "Unary": ["goto", "181"], "constant": ["s", "136"], "identifier": ["s", "137"], "Factor": ["goto", "138"], "false": ["s", "139"], "!": ["s", "140"]}, "164": {"-": ["s", "130"], "true": ["s", "131"], "(": ["s", "132"], "Loc": ["goto", "133"], "Unary": ["goto", "182"], "constant": ["s", "136"], "identifier": ["s", "137"], "Factor": ["goto", "138"], "false": ["s", "139"], "!": ["s", "140"]}, "165": {")": ["r", 36], "&&": ["r", 36], "!=": ["r", 36], "==": ["r", 36], "||": ["r", 36], "-": ["r", 36], "/": ["r", 36], "*": ["r", 36], "+": ["r", 36]}, "166": {"||": ["s", "92"], ")": ["s", "183"]}, "167": {"Term": ["goto", "184"], "-": ["s", "130"], "true": ["s", "131"], "(": ["s", "132"], "Loc": ["goto", "133"], "Unary": ["goto", "135"], "constant": ["s", "136"], "identifier": ["s", "137"], "Factor": ["goto", "138"], "false": ["s", "139"], "!": ["s", "140"]}, "168": {"Term": ["goto", "185"], "-": ["s", "130"], "true": ["s", "131"], "(": ["s", "132"], "Loc": ["goto", "133"], "Unary": ["goto", "135"], "constant": ["s", "136"], "identifier": ["s", "137"], "Factor": ["goto", "138"], "false": ["s", "139"], "!": ["s", "140"]}, "169": {")": ["r", 35], "&&": ["r", 35], "!=": ["r", 35], "==": ["r", 35], "||": ["r", 35], "-": ["r", 35], "/": ["r", 35], "*": ["r", 35], "+": ["r", 35]}, "170": {"Term": ["goto", "29"], "-": ["s", "30"], "true": ["s", "31"], "(": ["s", "32"], "Loc": ["goto", "33"], "Equality": ["goto", "34"], "Expr": ["goto", "35"], "Unary": ["goto", "36"], "constant": ["s", "37"], "identifier": ["s", "38"], "Bool": ["goto", "186"], "Factor": ["goto", "40"], "Join": ["goto", "41"], "false": ["s", "42"], "!": ["s", "43"], "Rel": ["goto", "44"]}, "171": {"Term": ["goto", "45"], "-": ["s", "46"], "true": ["s", "47"], "(": ["s", "48"], "Loc": ["goto", "49"], "Equality": ["goto", "50"], "Expr": ["goto", "51"], "Unary": ["goto", "52"], "constant": ["s", "53"], "identifier": ["s", "54"], "Bool": ["goto", "187"], "Factor": ["goto", "56"], "Join": ["goto", "57"], "false": ["s", "58"], "!": ["s", "59"], "Rel": ["goto", "60"]}, "172": {"Term": ["goto", "45"], "-": ["s", "46"], "true": ["s", "47"], "(": ["s", "48"], "Loc": ["goto", "49"], "Equality": ["goto", "50"], "Expr": ["goto", "51"], "Unary": ["goto", "52"], "constant": ["s", "53"], "identifier": ["s", "54"], "Bool": ["goto", "188"], "Factor": ["goto", "56"], "Join": ["goto", "57"], "false": ["s", "58"], "!": ["s", "59"], "Rel": ["goto", "60"]}, "173": {"Loc": ["goto", "13"], "if1": ["s", "14"], "if2": ["s", "16"], "Stmt": ["goto", "189"], "{": ["s", "18"], "identifier": ["s", "19"], "while": ["s", "21"], "Block": ["goto", "20"]}, "174": {"Stmts": ["goto", "190"], "bool": ["s", "8"], "Type": ["goto", "9"], "Decl": ["goto", "10"], "int": ["s", "11"], "float": ["s", "12"], "}": ["r", 10], "while": ["r", 10], "if2": ["r", 10], "if1": ["r", 10], "identifier": ["r", 10], "{": ["r", 10]}, "175": {"Term": ["goto", "45"], "-": ["s", "46"], "true": ["s", "47"], "(": ["s", "48"], "Loc": ["goto", "49"], "Equality": ["goto", "50"], "Expr": ["goto", "51"], "Unary": ["goto", "52"], "constant": ["s", "53"], "identifier": ["s", "54"], "Bool": ["goto", "191"], "Factor": ["goto", "56"], "Join": ["goto", "57"], "false": ["s", "58"], "!": ["s", "59"], "Rel": ["goto", "60"]}, "176": {";": ["r", 33], "||": ["r", 33], "&&": ["r", 33], "!=": ["r", 33], "==": ["r", 33], "-": ["r", 33], "/": ["r", 33], "*": ["r", 33], "+": ["r", 33]}, "177": {";": ["r", 32], "||": ["r", 32], "&&": ["r", 32], "!=": ["r", 32], "==": ["r", 32], "-": ["r", 32], "/": ["r", 32], "*": ["r", 32], "+": ["r", 32]}, "178": {";": ["r", 38], "||": ["r", 38], "&&": ["r", 38], "!=": ["r", 38], "==": ["r", 38], "-": ["r", 38], "/": ["r", 38], "*": ["r", 38], "+": ["r", 38]}, "179": {"/": ["s", "156"], "*": ["s", "157"], ";": ["r", 30], "||": ["r", 30], "&&": ["r", 30], "!=": ["r", 30], "==": ["r", 30], "-": ["r", 30], "+": ["r", 30]}, "180": {"/": ["s", "156"], "*": ["s", "157"], ";": ["r", 29], "||": ["r", 29], "&&": ["r", 29], "!=": ["r", 29], "==": ["r", 29], "-": ["r", 29], "+": ["r", 29]}, "181": {")": ["r", 33], "&&": ["r", 33], "!=": ["r", 33], "==": ["r", 33], "||": ["r", 33], "-": ["r", 33], "/": ["r", 33], "*": ["r", 33], "+": ["r", 33]}, "182": {")": ["r", 32], "&&": ["r", 32], "!=": ["r", 32], "==": ["r", 32], "||": ["r", 32], "-": ["r", 32], "/": ["r", 32], "*": ["r", 32], "+": ["r", 32]}, "183": {")": ["r", 38], "&&": ["r", 38], "!=": ["r", 38], "==": ["r", 38], "||": ["r", 38], "-": ["r", 38], "/": ["r", 38], "*": ["r", 38], "+": ["r", 38]}, "184": {"/": ["s", "163"], "*": ["s", "164"], ")": ["r", 30], "&&": ["r", 30], "!=": ["r", 30], "==": ["r", 30], "||": ["r", 30], "-": ["r", 30], "+": ["r", 30]}, "185": {"/": ["s", "163"], "*": ["s", "164"], ")": ["r", 29], "&&": ["r", 29], "!=": ["r", 29], "==": ["r", 29], "||": ["r", 29], "-": ["r", 29], "+": ["r", 29]}, "186": {";": ["s", "192"], "||": ["s", "77"]}, "187": {"||": ["s", "92"], ")": ["s", "193"]}, "188": {"||": ["s", "92"], ")": ["s", "194"]}, "189": {"}": ["r", 13], "if1": ["r", 13], "identifier": ["r", 13], "{": ["r", 13], "while": ["r", 13], "if2": ["r", 13]}, "190": {"Loc": ["goto", "13"], "if1": ["s", "14"], "}": ["s", "195"], "if2": ["s", "16"], "Stmt": ["goto", "17"], "{": ["s", "18"], "identifier": ["s", "19"], "Block": ["goto", "20"], "while": ["s", "21"]}, "191": {"||": ["s", "92"], ")": ["s", "196"]}, "192": {"else": ["r", 11]}, "193": {"Loc": ["goto", "148"], "if1": ["s", "149"], "if2": ["s", "150"], "Stmt": ["goto", "197"], "{": ["s", "152"], "identifier": ["s", "19"], "while": ["s", "153"], "Block": ["goto", "154"]}, "194": {"Loc": ["goto", "148"], "if1": ["s", "149"], "if2": ["s", "150"], "Stmt": ["goto", "198"], "{": ["s", "152"], "identifier": ["s", "19"], "while": ["s", "153"], "Block": ["goto", "154"]}, "195": {"else": ["r", 2]}, "196": {"Loc": ["goto", "148"], "if1": ["s", "149"], "if2": ["s", "150"], "Stmt": ["goto", "199"], "{": ["s", "152"], "identifier": ["s", "19"], "while": ["s", "153"], "Block": ["goto", "154"]}, "197": {"else": ["r", 12]}, "198": {"else": ["s", "200"]}, "199": {"else": ["r", 14]}, "200": {"Loc": ["goto", "148"], "if1": ["s", "149"], "if2": ["s", "150"], "Stmt": ["goto", "201"], "{": ["s", "152"], "identifier": ["s", "19"], "while": ["s", "153"], "Block": ["goto", "154"]}, "201": {"else": ["r", 13]}}